parse_this/__init__.py
parse_this/args.py
parse_this/call.py
parse_this/parsers.py
parse_this/parsing.py
parse_this/types.py
parse_this/values.py
test/__init__.py
test/core_test.py
test/parse_this_test.py
test/utils.py
parse_this-3.0.0.dist-info/LICENSE
parse_this-3.0.0.dist-info/METADATA
parse_this-3.0.0.dist-info/WHEEL
parse_this-3.0.0.dist-info/top_level.txt
parse_this-3.0.0.dist-info/RECORD
