Metadata-Version: 2.1
Name: parse-this
Version: 3.0.0
Summary: Makes it easy to create a command line interface for any function, method or classmethod..
Home-page: https://github.com/bertrandvidal/parse_this
Download-URL: https://pypi.python.org/pypi/parse_this
Author: Bertrand Vidal
Author-email: vidal.bertrand@gmail.com
License: License :: MIT
Platform: UNKNOWN
Classifier: Intended Audience :: Developers
Classifier: Intended Audience :: Information Technology
Classifier: Operating System :: OS Independent
Classifier: Programming Language :: Python :: 3 :: Only
Classifier: Programming Language :: Python :: 3.8
Classifier: Programming Language :: Python :: 3.9
Classifier: Programming Language :: Python :: 3.10
License-File: LICENSE
